nw_connections/__init__.py
nw_connections/cache.py
nw_connections/connection.py
nw_connections/postgrest.py
nw_connections/robotwriter.py
nw_connections/utils.py
nw_connections-1.5.0.dist-info/METADATA
nw_connections-1.5.0.dist-info/WHEEL
nw_connections-1.5.0.dist-info/top_level.txt
nw_connections-1.5.0.dist-info/RECORD
