Metadata-Version: 2.1
Name: nw-connections
Version: 1.5.0
Summary: Shared Marple python modules
Home-page: http://github.com/marple-newsrobot/newsworthy-py-connections
Author: Journalism Robotics Stockholm
Author-email: contact@newsworthy.se
License: MIT
Requires-Dist: boto3>=1.9
Requires-Dist: requests<3,>=2
Requires-Dist: requests-cache<2,>=1
Requires-Dist: PyJWT<2,>=1.7.1
Requires-Dist: requests-jwt<1,>=0.4
Requires-Dist: simplejson>=3
